sfHMM-0.8.0.dist-info/METADATA
sfHMM-0.8.0.dist-info/WHEEL
sfHMM-0.8.0.dist-info/entry_points.txt
sfHMM-0.8.0.dist-info/licenses/LICENSE
sfHMM/motor/__init__.py
sfHMM/motor/motor_sfhmm.py
sfHMM/motor/base.py
sfHMM/gmm.py
sfHMM/himena/widgets.py
sfHMM/himena/commands.py
sfHMM/himena/__init__.py
sfHMM/himena/consts.py
sfHMM/io/__init__.py
sfHMM/io/utils.py
sfHMM/io/pd.py
sfHMM/_sfhmm_ext.pyi
sfHMM/__init__.py
sfHMM/multi_sfhmm.py
sfHMM/sampling.py
sfHMM/utils.py
sfHMM/step/__init__.py
sfHMM/step/step.py
sfHMM/step/moment.py
sfHMM/viewer/__init__.py
sfHMM/viewer/mainwin.py
sfHMM/viewer/canvas.py
sfHMM/base.py
sfHMM/single_sfhmm.py
sfHMM/_sfhmm_ext.pypy311-pp73-x86_64-linux-gnu.so
sfHMM-0.8.0.dist-info/RECORD
