Metadata-Version: 2.4
Name: sfHMM
Version: 0.8.0
Classifier: Programming Language :: Rust
Classifier: Programming Language :: Python :: Implementation :: CPython
Classifier: Programming Language :: Python :: Implementation :: PyPy
Requires-Dist: numpy>=2.0.0
Requires-Dist: scipy>=1.7.0
Requires-Dist: pandas>=2.0.0
Requires-Dist: hmmlearn>=0.3.3
Requires-Dist: scikit-learn>=1.4.2
Requires-Dist: matplotlib>=3.10.0
Requires-Dist: pytest>=7.0 ; extra == 'dev'
Requires-Dist: pytest-cov>=4.0 ; extra == 'dev'
Requires-Dist: himena>=0.0.8 ; extra == 'himena'
Requires-Dist: cmap>=0.6.0 ; extra == 'himena'
Provides-Extra: dev
Provides-Extra: himena
License-File: LICENSE
Summary: step-finding-based HMM
Requires-Python: >=3.9
